islack/__init__.py
islack/incoming.py
islack-0.1.1.dist-info/LICENSE
islack-0.1.1.dist-info/METADATA
islack-0.1.1.dist-info/WHEEL
islack-0.1.1.dist-info/top_level.txt
islack-0.1.1.dist-info/RECORD
